anipose/__init__.py
anipose/anipose.py
anipose/calibrate.py
anipose/calibration_errors.py
anipose/common.py
anipose/compute_angles.py
anipose/convert_videos.py
anipose/extract_frames.py
anipose/filter_3d.py
anipose/filter_pose.py
anipose/label_combined.py
anipose/label_filter_compare.py
anipose/label_videos.py
anipose/label_videos_3d.py
anipose/label_videos_proj.py
anipose/pose_videos.py
anipose/project_2d.py
anipose/server.py
anipose/summarize.py
anipose/tracking_errors.py
anipose/train_autoencoder.py
anipose/triangulate.py
anipose/static/index.html
anipose/static/script.js
anipose/static/style.css
anipose/static/lib/babylon.js
anipose/static/lib/jquery-3.5.1.slim.js
anipose/static/lib/pep.js
anipose/static/lib/select2.min.css
anipose/static/lib/select2.min.js
anipose-1.1.24.dist-info/LICENSE
anipose-1.1.24.dist-info/METADATA
anipose-1.1.24.dist-info/WHEEL
anipose-1.1.24.dist-info/entry_points.txt
anipose-1.1.24.dist-info/top_level.txt
anipose-1.1.24.dist-info/RECORD
