Metadata-Version: 2.1
Name: anipose
Version: 1.1.24
Summary: Framework for scalable DeepLabCut based analysis including 3D tracking
Home-page: https://github.com/lambdaloop/anipose
Author: Lili Karashchuk
Author-email: krchtchk@gmail.com
Classifier: Programming Language :: Python :: 3
Classifier: License :: OSI Approved :: BSD License
Classifier: Intended Audience :: Science/Research
Classifier: Topic :: Scientific/Engineering
Classifier: Topic :: Scientific/Engineering :: Image Recognition
License-File: LICENSE
Requires-Dist: aniposelib >=0.7.0
Requires-Dist: opencv-contrib-python
Requires-Dist: toml
Requires-Dist: numpy
Requires-Dist: scipy
Requires-Dist: pandas
Requires-Dist: tqdm
Requires-Dist: click
Requires-Dist: scikit-video
Requires-Dist: flask
Requires-Dist: flask-compress
Requires-Dist: flask-ipban
Provides-Extra: dlc
Requires-Dist: deeplabcut >=2.0.4.1 ; extra == 'dlc'
Provides-Extra: viz
Requires-Dist: mayavi ; extra == 'viz'
